hyprland_autocompile/__init__.py
hyprland_autocompile-0.0.2a0.dist-info/METADATA
hyprland_autocompile-0.0.2a0.dist-info/WHEEL
hyprland_autocompile-0.0.2a0.dist-info/RECORD
